src/__init__.py
src/aws_in_docker/__init__.py
slurm_in_aws-0.0.1.dist-info/LICENSE
slurm_in_aws-0.0.1.dist-info/WHEEL
slurm_in_aws-0.0.1.dist-info/METADATA
slurm_in_aws-0.0.1.dist-info/RECORD
