Metadata-Version: 2.1
Name: slurm-in-aws
Version: 0.0.1
Summary: AWS plugin for Slurm
Author: Leo Gallucci
Author-email: elgalu3@gmail.com
Requires-Python: >=3.9,<4.0
Classifier: Development Status :: 4 - Beta
Classifier: Programming Language :: Python :: 3
Classifier: Programming Language :: Python :: 3 :: Only
Classifier: Programming Language :: Python :: 3.9
Requires-Dist: PyYAML (>=5.1,<6.0)
Requires-Dist: python_json_logger (>=0.1,<0.2)
